body3d/__init__.py
body3d/body3d.py
displycement-0.9.10.dist-info/licenses/LICENSE.txt
tensile/__init__.py
tensile/tensile.py
displycement-0.9.10.dist-info/METADATA
displycement-0.9.10.dist-info/WHEEL
displycement-0.9.10.dist-info/top_level.txt
displycement-0.9.10.dist-info/RECORD
