Metadata-Version: 2.4
Name: displycement
Version: 0.9.10
Summary: Python lib for analysis of tensile tests and 3D modeling
Author-email: Beñat Bastarrika <benat.bastarrika@alumuni.mondragon.edu>, Aitor Iriondo <aitor.iriondo@alumuni.mondragon.edu>, Ander Lizarazu <ander.lizarazu@alumuni.mondragon.edu>, Unai Ramirez <unai.ramirez@alumuni.mondragon.edu>
License: MIT
Project-URL: Homepage, https://github.com/tuusuario/xxx
Project-URL: Documentation, https://github.com/tuusuario/xxx
Project-URL: Repository, https://github.com/tuusuario/xxx
Project-URL: Issues, https://github.com/tuusuario/xxx/issues
Keywords: 3d,body3d,tensile,analysis,biomechanics
Classifier: Programming Language :: Python :: 3
Classifier: License :: OSI Approved :: MIT License
Classifier: Operating System :: OS Independent
Requires-Python: >=3.9
License-File: LICENSE.txt
Requires-Dist: opencv-python
Requires-Dist: numpy
Requires-Dist: pandas
Requires-Dist: matplotlib
Dynamic: license-file
